fairaudit/__init__.py
fairaudit/auditor.py
fairaudit/bootstrap.py
fairaudit/flag.py
fairaudit/groups.py
fairaudit/metrics.py
fairaudit/shifts.py
fairaudit-0.0.1.dist-info/METADATA
fairaudit-0.0.1.dist-info/WHEEL
fairaudit-0.0.1.dist-info/top_level.txt
fairaudit-0.0.1.dist-info/RECORD
