Metadata-Version: 2.1
Name: fairaudit
Version: 0.0.1
Summary: This package enables fairness auditing with statistical guarantees.
Home-page: https://github.com/jjcherian/fairaudit
Author: John Cherian
Author-email: John Cherian <jcherian@stanford.edu>
Project-URL: Homepage, https://github.com/jjcherian/fairaudit
Project-URL: Bug Tracker, https://github.com/jjcherian/fairaudit/issues
Classifier: Programming Language :: Python :: 3
Classifier: License :: OSI Approved :: MIT License
Classifier: Operating System :: OS Independent
Requires-Python: >=3.7
Requires-Dist: numpy
Requires-Dist: scipy
Requires-Dist: cvxpy
Requires-Dist: scikit-learn
Requires-Dist: matplotlib
Requires-Dist: statsmodels
Requires-Dist: tqdm
